<annotation>
	<folder>pollos_r</folder>
	<filename>R155.jpg</filename>
	<path>/pollos_r/R155.jpg</path>
	<source>
		<database>Unspecified</database>
	</source>
	<size>
		<width>3472</width>
		<height>4624</height>
		<depth>3</depth>
	</size>
	<object>
		<name>Pollos</name>
		<pose>Unspecified</pose>
		<truncated>0</truncated>
		<difficult>0</difficult>
		<bndbox>
			<xmin>396</xmin>
			<ymin>3521</ymin>
			<xmax>2058</xmax>
			<ymax>4624</ymax>
		</bndbox>
	</object>
	<object>
		<name>Pollos</name>
		<pose>Unspecified</pose>
		<truncated>0</truncated>
		<difficult>0</difficult>
		<bndbox>
			<xmin>1061</xmin>
			<ymin>2728</ymin>
			<xmax>2482</xmax>
			<ymax>3460</ymax>
		</bndbox>
	</object>
	<object>
		<name>Pollos</name>
		<pose>Unspecified</pose>
		<truncated>0</truncated>
		<difficult>0</difficult>
		<bndbox>
			<xmin>1960</xmin>
			<ymin>1927</ymin>
			<xmax>3018</xmax>
			<ymax>2765</ymax>
		</bndbox>
	</object>
	<object>
		<name>Pollos</name>
		<pose>Unspecified</pose>
		<truncated>0</truncated>
		<difficult>0</difficult>
		<bndbox>
			<xmin>2330</xmin>
			<ymin>1209</ymin>
			<xmax>3184</xmax>
			<ymax>1957</ymax>
		</bndbox>
	</object>
	<object>
		<name>Pollos</name>
		<pose>Unspecified</pose>
		<truncated>0</truncated>
		<difficult>0</difficult>
		<bndbox>
			<xmin>2678</xmin>
			<ymin>922</ymin>
			<xmax>3441</xmax>
			<ymax>1292</ymax>
		</bndbox>
	</object>
	<object>
		<name>Pollos</name>
		<pose>Unspecified</pose>
		<truncated>0</truncated>
		<difficult>0</difficult>
		<bndbox>
			<xmin>0</xmin>
			<ymin>1685</ymin>
			<xmax>789</xmax>
			<ymax>2992</ymax>
		</bndbox>
	</object>
	<object>
		<name>Pollos</name>
		<pose>Unspecified</pose>
		<truncated>0</truncated>
		<difficult>0</difficult>
		<bndbox>
			<xmin>865</xmin>
			<ymin>876</ymin>
			<xmax>1635</xmax>
			<ymax>1715</ymax>
		</bndbox>
	</object>
	<object>
		<name>Pollos</name>
		<pose>Unspecified</pose>
		<truncated>0</truncated>
		<difficult>0</difficult>
		<bndbox>
			<xmin>1658</xmin>
			<ymin>793</ymin>
			<xmax>2194</xmax>
			<ymax>1519</ymax>
		</bndbox>
	</object>
	<object>
		<name>Pollos</name>
		<pose>Unspecified</pose>
		<truncated>0</truncated>
		<difficult>0</difficult>
		<bndbox>
			<xmin>1658</xmin>
			<ymin>536</ymin>
			<xmax>2270</xmax>
			<ymax>914</ymax>
		</bndbox>
	</object>
	<object>
		<name>Pollos</name>
		<pose>Unspecified</pose>
		<truncated>0</truncated>
		<difficult>0</difficult>
		<bndbox>
			<xmin>298</xmin>
			<ymin>1050</ymin>
			<xmax>736</xmax>
			<ymax>1451</ymax>
		</bndbox>
	</object>
	<object>
		<name>Pollos</name>
		<pose>Unspecified</pose>
		<truncated>0</truncated>
		<difficult>0</difficult>
		<bndbox>
			<xmin>94</xmin>
			<ymin>763</ymin>
			<xmax>479</xmax>
			<ymax>1148</ymax>
		</bndbox>
	</object>
	<object>
		<name>Pollos</name>
		<pose>Unspecified</pose>
		<truncated>0</truncated>
		<difficult>0</difficult>
		<bndbox>
			<xmin>1054</xmin>
			<ymin>348</ymin>
			<xmax>1462</xmax>
			<ymax>604</ymax>
		</bndbox>
	</object>
	<object>
		<name>Pollos</name>
		<pose>Unspecified</pose>
		<truncated>0</truncated>
		<difficult>0</difficult>
		<bndbox>
			<xmin>1779</xmin>
			<ymin>196</ymin>
			<xmax>2376</xmax>
			<ymax>348</ymax>
		</bndbox>
	</object>
	<object>
		<name>Pollos</name>
		<pose>Unspecified</pose>
		<truncated>0</truncated>
		<difficult>0</difficult>
		<bndbox>
			<xmin>2754</xmin>
			<ymin>174</ymin>
			<xmax>3124</xmax>
			<ymax>400</ymax>
		</bndbox>
	</object>
	<object>
		<name>Pollos</name>
		<pose>Unspecified</pose>
		<truncated>0</truncated>
		<difficult>0</difficult>
		<bndbox>
			<xmin>94</xmin>
			<ymin>400</ymin>
			<xmax>472</xmax>
			<ymax>688</ymax>
		</bndbox>
	</object>
</annotation>