<annotation>
	<folder>pollos_r</folder>
	<filename>R170.jpg</filename>
	<path>/pollos_r/R170.jpg</path>
	<source>
		<database>Unspecified</database>
	</source>
	<size>
		<width>3472</width>
		<height>4624</height>
		<depth>3</depth>
	</size>
	<object>
		<name>Pollos</name>
		<pose>Unspecified</pose>
		<truncated>0</truncated>
		<difficult>0</difficult>
		<bndbox>
			<xmin>200</xmin>
			<ymin>1798</ymin>
			<xmax>1069</xmax>
			<ymax>2690</ymax>
		</bndbox>
	</object>
	<object>
		<name>Pollos</name>
		<pose>Unspecified</pose>
		<truncated>0</truncated>
		<difficult>0</difficult>
		<bndbox>
			<xmin>948</xmin>
			<ymin>1541</ymin>
			<xmax>1560</xmax>
			<ymax>2002</ymax>
		</bndbox>
	</object>
	<object>
		<name>Pollos</name>
		<pose>Unspecified</pose>
		<truncated>0</truncated>
		<difficult>0</difficult>
		<bndbox>
			<xmin>2814</xmin>
			<ymin>2501</ymin>
			<xmax>3252</xmax>
			<ymax>2924</ymax>
		</bndbox>
	</object>
	<object>
		<name>Pollos</name>
		<pose>Unspecified</pose>
		<truncated>0</truncated>
		<difficult>0</difficult>
		<bndbox>
			<xmin>2610</xmin>
			<ymin>2947</ymin>
			<xmax>3071</xmax>
			<ymax>3430</ymax>
		</bndbox>
	</object>
	<object>
		<name>Pollos</name>
		<pose>Unspecified</pose>
		<truncated>0</truncated>
		<difficult>0</difficult>
		<bndbox>
			<xmin>2225</xmin>
			<ymin>2131</ymin>
			<xmax>2686</xmax>
			<ymax>2629</ymax>
		</bndbox>
	</object>
	<object>
		<name>Pollos</name>
		<pose>Unspecified</pose>
		<truncated>0</truncated>
		<difficult>0</difficult>
		<bndbox>
			<xmin>2791</xmin>
			<ymin>1179</ymin>
			<xmax>3048</xmax>
			<ymax>1556</ymax>
		</bndbox>
	</object>
	<object>
		<name>Pollos</name>
		<pose>Unspecified</pose>
		<truncated>0</truncated>
		<difficult>0</difficult>
		<bndbox>
			<xmin>593</xmin>
			<ymin>196</ymin>
			<xmax>978</xmax>
			<ymax>688</ymax>
		</bndbox>
	</object>
	<object>
		<name>Pollos</name>
		<pose>Unspecified</pose>
		<truncated>0</truncated>
		<difficult>0</difficult>
		<bndbox>
			<xmin>260</xmin>
			<ymin>38</ymin>
			<xmax>698</xmax>
			<ymax>423</ymax>
		</bndbox>
	</object>
	<object>
		<name>Pollos</name>
		<pose>Unspecified</pose>
		<truncated>0</truncated>
		<difficult>0</difficult>
		<bndbox>
			<xmin>1545</xmin>
			<ymin>242</ymin>
			<xmax>1900</xmax>
			<ymax>506</ymax>
		</bndbox>
	</object>
	<object>
		<name>Pollos</name>
		<pose>Unspecified</pose>
		<truncated>0</truncated>
		<difficult>0</difficult>
		<bndbox>
			<xmin>1862</xmin>
			<ymin>431</ymin>
			<xmax>2149</xmax>
			<ymax>778</ymax>
		</bndbox>
	</object>
	<object>
		<name>Pollos</name>
		<pose>Unspecified</pose>
		<truncated>0</truncated>
		<difficult>0</difficult>
		<bndbox>
			<xmin>2338</xmin>
			<ymin>635</ymin>
			<xmax>2557</xmax>
			<ymax>884</ymax>
		</bndbox>
	</object>
	<object>
		<name>Pollos</name>
		<pose>Unspecified</pose>
		<truncated>0</truncated>
		<difficult>0</difficult>
		<bndbox>
			<xmin>1084</xmin>
			<ymin>831</ymin>
			<xmax>1734</xmax>
			<ymax>1330</ymax>
		</bndbox>
	</object>
	<object>
		<name>Pollos</name>
		<pose>Unspecified</pose>
		<truncated>0</truncated>
		<difficult>0</difficult>
		<bndbox>
			<xmin>2980</xmin>
			<ymin>914</ymin>
			<xmax>3192</xmax>
			<ymax>1179</ymax>
		</bndbox>
	</object>
	<object>
		<name>Pollos</name>
		<pose>Unspecified</pose>
		<truncated>0</truncated>
		<difficult>0</difficult>
		<bndbox>
			<xmin>2149</xmin>
			<ymin>45</ymin>
			<xmax>2353</xmax>
			<ymax>257</ymax>
		</bndbox>
	</object>
	<object>
		<name>Pollos</name>
		<pose>Unspecified</pose>
		<truncated>0</truncated>
		<difficult>0</difficult>
		<bndbox>
			<xmin>2406</xmin>
			<ymin>302</ymin>
			<xmax>2610</xmax>
			<ymax>536</ymax>
		</bndbox>
	</object>
	<object>
		<name>Pollos</name>
		<pose>Unspecified</pose>
		<truncated>0</truncated>
		<difficult>0</difficult>
		<bndbox>
			<xmin>2716</xmin>
			<ymin>468</ymin>
			<xmax>2935</xmax>
			<ymax>688</ymax>
		</bndbox>
	</object>
</annotation>