<annotation>
	<folder>pollos_r</folder>
	<filename>R179.jpg</filename>
	<path>/pollos_r/R179.jpg</path>
	<source>
		<database>Unspecified</database>
	</source>
	<size>
		<width>3472</width>
		<height>4624</height>
		<depth>3</depth>
	</size>
	<object>
		<name>Pollos</name>
		<pose>Unspecified</pose>
		<truncated>0</truncated>
		<difficult>0</difficult>
		<bndbox>
			<xmin>963</xmin>
			<ymin>2690</ymin>
			<xmax>1605</xmax>
			<ymax>3105</ymax>
		</bndbox>
	</object>
	<object>
		<name>Pollos</name>
		<pose>Unspecified</pose>
		<truncated>0</truncated>
		<difficult>0</difficult>
		<bndbox>
			<xmin>1892</xmin>
			<ymin>3083</ymin>
			<xmax>2565</xmax>
			<ymax>3695</ymax>
		</bndbox>
	</object>
	<object>
		<name>Pollos</name>
		<pose>Unspecified</pose>
		<truncated>0</truncated>
		<difficult>0</difficult>
		<bndbox>
			<xmin>1756</xmin>
			<ymin>2697</ymin>
			<xmax>2459</xmax>
			<ymax>3075</ymax>
		</bndbox>
	</object>
	<object>
		<name>Pollos</name>
		<pose>Unspecified</pose>
		<truncated>0</truncated>
		<difficult>0</difficult>
		<bndbox>
			<xmin>1696</xmin>
			<ymin>2312</ymin>
			<xmax>2217</xmax>
			<ymax>2682</ymax>
		</bndbox>
	</object>
	<object>
		<name>Pollos</name>
		<pose>Unspecified</pose>
		<truncated>0</truncated>
		<difficult>0</difficult>
		<bndbox>
			<xmin>1008</xmin>
			<ymin>2380</ymin>
			<xmax>1394</xmax>
			<ymax>2705</ymax>
		</bndbox>
	</object>
	<object>
		<name>Pollos</name>
		<pose>Unspecified</pose>
		<truncated>0</truncated>
		<difficult>0</difficult>
		<bndbox>
			<xmin>525</xmin>
			<ymin>2357</ymin>
			<xmax>872</xmax>
			<ymax>2622</ymax>
		</bndbox>
	</object>
	<object>
		<name>Pollos</name>
		<pose>Unspecified</pose>
		<truncated>0</truncated>
		<difficult>0</difficult>
		<bndbox>
			<xmin>102</xmin>
			<ymin>2327</ymin>
			<xmax>494</xmax>
			<ymax>2622</ymax>
		</bndbox>
	</object>
	<object>
		<name>Pollos</name>
		<pose>Unspecified</pose>
		<truncated>0</truncated>
		<difficult>0</difficult>
		<bndbox>
			<xmin>11</xmin>
			<ymin>2728</ymin>
			<xmax>336</xmax>
			<ymax>3068</ymax>
		</bndbox>
	</object>
	<object>
		<name>Pollos</name>
		<pose>Unspecified</pose>
		<truncated>0</truncated>
		<difficult>0</difficult>
		<bndbox>
			<xmin>1197</xmin>
			<ymin>2184</ymin>
			<xmax>1530</xmax>
			<ymax>2327</ymax>
		</bndbox>
	</object>
	<object>
		<name>Pollos</name>
		<pose>Unspecified</pose>
		<truncated>0</truncated>
		<difficult>0</difficult>
		<bndbox>
			<xmin>2187</xmin>
			<ymin>2327</ymin>
			<xmax>2451</xmax>
			<ymax>2667</ymax>
		</bndbox>
	</object>
</annotation>