<annotation>
	<folder>my-project-name</folder>
	<filename>319q.jpg</filename>
	<path>/my-project-name/319q.jpg</path>
	<source>
		<database>Unspecified</database>
	</source>
	<size>
		<width>3472</width>
		<height>4640</height>
		<depth>3</depth>
	</size>
	<object>
		<name>Pollos</name>
		<pose>Unspecified</pose>
		<truncated>0</truncated>
		<difficult>0</difficult>
		<bndbox>
			<xmin>3089</xmin>
			<ymin>3246</ymin>
			<xmax>3472</xmax>
			<ymax>4345</ymax>
		</bndbox>
	</object>
	<object>
		<name>Pollos</name>
		<pose>Unspecified</pose>
		<truncated>0</truncated>
		<difficult>0</difficult>
		<bndbox>
			<xmin>2377</xmin>
			<ymin>4070</ymin>
			<xmax>3472</xmax>
			<ymax>4640</ymax>
		</bndbox>
	</object>
	<object>
		<name>Pollos</name>
		<pose>Unspecified</pose>
		<truncated>0</truncated>
		<difficult>0</difficult>
		<bndbox>
			<xmin>2428</xmin>
			<ymin>3368</ymin>
			<xmax>3110</xmax>
			<ymax>4050</ymax>
		</bndbox>
	</object>
	<object>
		<name>Pollos</name>
		<pose>Unspecified</pose>
		<truncated>0</truncated>
		<difficult>0</difficult>
		<bndbox>
			<xmin>1573</xmin>
			<ymin>3215</ymin>
			<xmax>2397</xmax>
			<ymax>3897</ymax>
		</bndbox>
	</object>
	<object>
		<name>Pollos</name>
		<pose>Unspecified</pose>
		<truncated>0</truncated>
		<difficult>0</difficult>
		<bndbox>
			<xmin>1431</xmin>
			<ymin>3948</ymin>
			<xmax>2377</xmax>
			<ymax>4640</ymax>
		</bndbox>
	</object>
	<object>
		<name>Pollos</name>
		<pose>Unspecified</pose>
		<truncated>0</truncated>
		<difficult>0</difficult>
		<bndbox>
			<xmin>820</xmin>
			<ymin>3460</ymin>
			<xmax>1716</xmax>
			<ymax>4467</ymax>
		</bndbox>
	</object>
	<object>
		<name>Pollos</name>
		<pose>Unspecified</pose>
		<truncated>0</truncated>
		<difficult>0</difficult>
		<bndbox>
			<xmin>586</xmin>
			<ymin>2564</ymin>
			<xmax>1482</xmax>
			<ymax>3653</ymax>
		</bndbox>
	</object>
	<object>
		<name>Pollos</name>
		<pose>Unspecified</pose>
		<truncated>0</truncated>
		<difficult>0</difficult>
		<bndbox>
			<xmin>1746</xmin>
			<ymin>1638</ymin>
			<xmax>2784</xmax>
			<ymax>2422</ymax>
		</bndbox>
	</object>
	<object>
		<name>Pollos</name>
		<pose>Unspecified</pose>
		<truncated>0</truncated>
		<difficult>0</difficult>
		<bndbox>
			<xmin>2692</xmin>
			<ymin>2198</ymin>
			<xmax>3456</xmax>
			<ymax>3195</ymax>
		</bndbox>
	</object>
	<object>
		<name>Pollos</name>
		<pose>Unspecified</pose>
		<truncated>0</truncated>
		<difficult>0</difficult>
		<bndbox>
			<xmin>1777</xmin>
			<ymin>2534</ymin>
			<xmax>2794</xmax>
			<ymax>3399</ymax>
		</bndbox>
	</object>
	<object>
		<name>Pollos</name>
		<pose>Unspecified</pose>
		<truncated>0</truncated>
		<difficult>0</difficult>
		<bndbox>
			<xmin>0</xmin>
			<ymin>1587</ymin>
			<xmax>861</xmax>
			<ymax>2188</ymax>
		</bndbox>
	</object>
	<object>
		<name>Pollos</name>
		<pose>Unspecified</pose>
		<truncated>0</truncated>
		<difficult>0</difficult>
		<bndbox>
			<xmin>413</xmin>
			<ymin>702</ymin>
			<xmax>1187</xmax>
			<ymax>1740</ymax>
		</bndbox>
	</object>
	<object>
		<name>Pollos</name>
		<pose>Unspecified</pose>
		<truncated>0</truncated>
		<difficult>0</difficult>
		<bndbox>
			<xmin>983</xmin>
			<ymin>315</ymin>
			<xmax>1665</xmax>
			<ymax>1374</ymax>
		</bndbox>
	</object>
	<object>
		<name>Pollos</name>
		<pose>Unspecified</pose>
		<truncated>0</truncated>
		<difficult>0</difficult>
		<bndbox>
			<xmin>1553</xmin>
			<ymin>509</ymin>
			<xmax>2458</xmax>
			<ymax>1353</ymax>
		</bndbox>
	</object>
	<object>
		<name>Pollos</name>
		<pose>Unspecified</pose>
		<truncated>0</truncated>
		<difficult>0</difficult>
		<bndbox>
			<xmin>2184</xmin>
			<ymin>20</ymin>
			<xmax>2845</xmax>
			<ymax>784</ymax>
		</bndbox>
	</object>
	<object>
		<name>Pollos</name>
		<pose>Unspecified</pose>
		<truncated>0</truncated>
		<difficult>0</difficult>
		<bndbox>
			<xmin>1288</xmin>
			<ymin>0</ymin>
			<xmax>2163</xmax>
			<ymax>438</ymax>
		</bndbox>
	</object>
	<object>
		<name>Pollos</name>
		<pose>Unspecified</pose>
		<truncated>0</truncated>
		<difficult>0</difficult>
		<bndbox>
			<xmin>0</xmin>
			<ymin>356</ymin>
			<xmax>678</xmax>
			<ymax>1119</ymax>
		</bndbox>
	</object>
</annotation>