<annotation>
	<folder>polllos-401</folder>
	<filename>437q.jpg</filename>
	<path>/polllos-401/437q.jpg</path>
	<source>
		<database>Unspecified</database>
	</source>
	<size>
		<width>3472</width>
		<height>4640</height>
		<depth>3</depth>
	</size>
	<object>
		<name>Pollos</name>
		<pose>Unspecified</pose>
		<truncated>0</truncated>
		<difficult>0</difficult>
		<bndbox>
			<xmin>1497</xmin>
			<ymin>3721</ymin>
			<xmax>1864</xmax>
			<ymax>4145</ymax>
		</bndbox>
	</object>
	<object>
		<name>Pollos</name>
		<pose>Unspecified</pose>
		<truncated>0</truncated>
		<difficult>0</difficult>
		<bndbox>
			<xmin>1925</xmin>
			<ymin>3596</ymin>
			<xmax>2209</xmax>
			<ymax>4020</ymax>
		</bndbox>
	</object>
	<object>
		<name>Pollos</name>
		<pose>Unspecified</pose>
		<truncated>0</truncated>
		<difficult>0</difficult>
		<bndbox>
			<xmin>2115</xmin>
			<ymin>3380</ymin>
			<xmax>2353</xmax>
			<ymax>3687</ymax>
		</bndbox>
	</object>
	<object>
		<name>Pollos</name>
		<pose>Unspecified</pose>
		<truncated>0</truncated>
		<difficult>0</difficult>
		<bndbox>
			<xmin>2213</xmin>
			<ymin>2891</ymin>
			<xmax>2520</xmax>
			<ymax>3205</ymax>
		</bndbox>
	</object>
	<object>
		<name>Pollos</name>
		<pose>Unspecified</pose>
		<truncated>0</truncated>
		<difficult>0</difficult>
		<bndbox>
			<xmin>1925</xmin>
			<ymin>2735</ymin>
			<xmax>2278</xmax>
			<ymax>2974</ymax>
		</bndbox>
	</object>
	<object>
		<name>Pollos</name>
		<pose>Unspecified</pose>
		<truncated>0</truncated>
		<difficult>0</difficult>
		<bndbox>
			<xmin>1792</xmin>
			<ymin>3084</ymin>
			<xmax>2043</xmax>
			<ymax>3292</ymax>
		</bndbox>
	</object>
	<object>
		<name>Pollos</name>
		<pose>Unspecified</pose>
		<truncated>0</truncated>
		<difficult>0</difficult>
		<bndbox>
			<xmin>1618</xmin>
			<ymin>3198</ymin>
			<xmax>1887</xmax>
			<ymax>3436</ymax>
		</bndbox>
	</object>
	<object>
		<name>Pollos</name>
		<pose>Unspecified</pose>
		<truncated>0</truncated>
		<difficult>0</difficult>
		<bndbox>
			<xmin>754</xmin>
			<ymin>3027</ymin>
			<xmax>1091</xmax>
			<ymax>3463</ymax>
		</bndbox>
	</object>
	<object>
		<name>Pollos</name>
		<pose>Unspecified</pose>
		<truncated>0</truncated>
		<difficult>0</difficult>
		<bndbox>
			<xmin>792</xmin>
			<ymin>2591</ymin>
			<xmax>1110</xmax>
			<ymax>2902</ymax>
		</bndbox>
	</object>
	<object>
		<name>Pollos</name>
		<pose>Unspecified</pose>
		<truncated>0</truncated>
		<difficult>0</difficult>
		<bndbox>
			<xmin>185</xmin>
			<ymin>2743</ymin>
			<xmax>697</xmax>
			<ymax>3046</ymax>
		</bndbox>
	</object>
	<object>
		<name>Pollos</name>
		<pose>Unspecified</pose>
		<truncated>0</truncated>
		<difficult>0</difficult>
		<bndbox>
			<xmin>177</xmin>
			<ymin>3035</ymin>
			<xmax>564</xmax>
			<ymax>3565</ymax>
		</bndbox>
	</object>
	<object>
		<name>Pollos</name>
		<pose>Unspecified</pose>
		<truncated>0</truncated>
		<difficult>0</difficult>
		<bndbox>
			<xmin>409</xmin>
			<ymin>2072</ymin>
			<xmax>761</xmax>
			<ymax>2322</ymax>
		</bndbox>
	</object>
	<object>
		<name>Pollos</name>
		<pose>Unspecified</pose>
		<truncated>0</truncated>
		<difficult>0</difficult>
		<bndbox>
			<xmin>0</xmin>
			<ymin>1920</ymin>
			<xmax>367</xmax>
			<ymax>2273</ymax>
		</bndbox>
	</object>
	<object>
		<name>Pollos</name>
		<pose>Unspecified</pose>
		<truncated>0</truncated>
		<difficult>0</difficult>
		<bndbox>
			<xmin>1963</xmin>
			<ymin>2405</ymin>
			<xmax>2289</xmax>
			<ymax>2667</ymax>
		</bndbox>
	</object>
	<object>
		<name>Pollos</name>
		<pose>Unspecified</pose>
		<truncated>0</truncated>
		<difficult>0</difficult>
		<bndbox>
			<xmin>2505</xmin>
			<ymin>1992</ymin>
			<xmax>2827</xmax>
			<ymax>2288</ymax>
		</bndbox>
	</object>
	<object>
		<name>Pollos</name>
		<pose>Unspecified</pose>
		<truncated>0</truncated>
		<difficult>0</difficult>
		<bndbox>
			<xmin>1834</xmin>
			<ymin>2098</ymin>
			<xmax>2111</xmax>
			<ymax>2360</ymax>
		</bndbox>
	</object>
	<object>
		<name>Pollos</name>
		<pose>Unspecified</pose>
		<truncated>0</truncated>
		<difficult>0</difficult>
		<bndbox>
			<xmin>2334</xmin>
			<ymin>2474</ymin>
			<xmax>2626</xmax>
			<ymax>2830</ymax>
		</bndbox>
	</object>
	<object>
		<name>Pollos</name>
		<pose>Unspecified</pose>
		<truncated>0</truncated>
		<difficult>0</difficult>
		<bndbox>
			<xmin>610</xmin>
			<ymin>1780</ymin>
			<xmax>883</xmax>
			<ymax>1954</ymax>
		</bndbox>
	</object>
	<object>
		<name>Pollos</name>
		<pose>Unspecified</pose>
		<truncated>0</truncated>
		<difficult>0</difficult>
		<bndbox>
			<xmin>610</xmin>
			<ymin>1552</ymin>
			<xmax>792</xmax>
			<ymax>1757</ymax>
		</bndbox>
	</object>
	<object>
		<name>Pollos</name>
		<pose>Unspecified</pose>
		<truncated>0</truncated>
		<difficult>0</difficult>
		<bndbox>
			<xmin>378</xmin>
			<ymin>1966</ymin>
			<xmax>856</xmax>
			<ymax>2106</ymax>
		</bndbox>
	</object>
	<object>
		<name>Pollos</name>
		<pose>Unspecified</pose>
		<truncated>0</truncated>
		<difficult>0</difficult>
		<bndbox>
			<xmin>1906</xmin>
			<ymin>1863</ymin>
			<xmax>2058</xmax>
			<ymax>1985</ymax>
		</bndbox>
	</object>
	<object>
		<name>Pollos</name>
		<pose>Unspecified</pose>
		<truncated>0</truncated>
		<difficult>0</difficult>
		<bndbox>
			<xmin>1694</xmin>
			<ymin>1799</ymin>
			<xmax>1876</xmax>
			<ymax>1920</ymax>
		</bndbox>
	</object>
	<object>
		<name>Pollos</name>
		<pose>Unspecified</pose>
		<truncated>0</truncated>
		<difficult>0</difficult>
		<bndbox>
			<xmin>1660</xmin>
			<ymin>1947</ymin>
			<xmax>1906</xmax>
			<ymax>2174</ymax>
		</bndbox>
	</object>
	<object>
		<name>Pollos</name>
		<pose>Unspecified</pose>
		<truncated>0</truncated>
		<difficult>0</difficult>
		<bndbox>
			<xmin>1925</xmin>
			<ymin>1522</ymin>
			<xmax>2134</xmax>
			<ymax>1799</ymax>
		</bndbox>
	</object>
	<object>
		<name>Pollos</name>
		<pose>Unspecified</pose>
		<truncated>0</truncated>
		<difficult>0</difficult>
		<bndbox>
			<xmin>1588</xmin>
			<ymin>1367</ymin>
			<xmax>1819</xmax>
			<ymax>1480</ymax>
		</bndbox>
	</object>
	<object>
		<name>Pollos</name>
		<pose>Unspecified</pose>
		<truncated>0</truncated>
		<difficult>0</difficult>
		<bndbox>
			<xmin>920</xmin>
			<ymin>1143</ymin>
			<xmax>1057</xmax>
			<ymax>1344</ymax>
		</bndbox>
	</object>
	<object>
		<name>Pollos</name>
		<pose>Unspecified</pose>
		<truncated>0</truncated>
		<difficult>0</difficult>
		<bndbox>
			<xmin>1072</xmin>
			<ymin>1234</ymin>
			<xmax>1193</xmax>
			<ymax>1359</ymax>
		</bndbox>
	</object>
	<object>
		<name>Pollos</name>
		<pose>Unspecified</pose>
		<truncated>0</truncated>
		<difficult>0</difficult>
		<bndbox>
			<xmin>1072</xmin>
			<ymin>1295</ymin>
			<xmax>1262</xmax>
			<ymax>1647</ymax>
		</bndbox>
	</object>
	<object>
		<name>Pollos</name>
		<pose>Unspecified</pose>
		<truncated>0</truncated>
		<difficult>0</difficult>
		<bndbox>
			<xmin>1228</xmin>
			<ymin>1484</ymin>
			<xmax>1626</xmax>
			<ymax>1712</ymax>
		</bndbox>
	</object>
	<object>
		<name>Pollos</name>
		<pose>Unspecified</pose>
		<truncated>0</truncated>
		<difficult>0</difficult>
		<bndbox>
			<xmin>1368</xmin>
			<ymin>1279</ymin>
			<xmax>1572</xmax>
			<ymax>1450</ymax>
		</bndbox>
	</object>
	<object>
		<name>Pollos</name>
		<pose>Unspecified</pose>
		<truncated>0</truncated>
		<difficult>0</difficult>
		<bndbox>
			<xmin>2558</xmin>
			<ymin>1749</ymin>
			<xmax>2706</xmax>
			<ymax>1950</ymax>
		</bndbox>
	</object>
	<object>
		<name>Pollos</name>
		<pose>Unspecified</pose>
		<truncated>0</truncated>
		<difficult>0</difficult>
		<bndbox>
			<xmin>2187</xmin>
			<ymin>2269</ymin>
			<xmax>2471</xmax>
			<ymax>2466</ymax>
		</bndbox>
	</object>
	<object>
		<name>Pollos</name>
		<pose>Unspecified</pose>
		<truncated>0</truncated>
		<difficult>0</difficult>
		<bndbox>
			<xmin>314</xmin>
			<ymin>1658</ymin>
			<xmax>572</xmax>
			<ymax>1928</ymax>
		</bndbox>
	</object>
	<object>
		<name>Pollos</name>
		<pose>Unspecified</pose>
		<truncated>0</truncated>
		<difficult>0</difficult>
		<bndbox>
			<xmin>1193</xmin>
			<ymin>3838</ymin>
			<xmax>1569</xmax>
			<ymax>4240</ymax>
		</bndbox>
	</object>
</annotation>