<annotation>
	<folder>p</folder>
	<filename>649.png</filename>
	<path>/p/649.png</path>
	<source>
		<database>Unspecified</database>
	</source>
	<size>
		<width>1920</width>
		<height>1080</height>
		<depth>3</depth>
	</size>
	<object>
		<name>Pollos</name>
		<pose>Unspecified</pose>
		<truncated>0</truncated>
		<difficult>0</difficult>
		<bndbox>
			<xmin>813</xmin>
			<ymin>397</ymin>
			<xmax>1010</xmax>
			<ymax>637</ymax>
		</bndbox>
	</object>
	<object>
		<name>Pollos</name>
		<pose>Unspecified</pose>
		<truncated>0</truncated>
		<difficult>0</difficult>
		<bndbox>
			<xmin>1099</xmin>
			<ymin>298</ymin>
			<xmax>1354</xmax>
			<ymax>517</ymax>
		</bndbox>
	</object>
	<object>
		<name>Pollos</name>
		<pose>Unspecified</pose>
		<truncated>0</truncated>
		<difficult>0</difficult>
		<bndbox>
			<xmin>1169</xmin>
			<ymin>24</ymin>
			<xmax>1366</xmax>
			<ymax>232</ymax>
		</bndbox>
	</object>
	<object>
		<name>Pollos</name>
		<pose>Unspecified</pose>
		<truncated>0</truncated>
		<difficult>0</difficult>
		<bndbox>
			<xmin>1266</xmin>
			<ymin>110</ymin>
			<xmax>1470</xmax>
			<ymax>343</ymax>
		</bndbox>
	</object>
	<object>
		<name>Pollos</name>
		<pose>Unspecified</pose>
		<truncated>0</truncated>
		<difficult>0</difficult>
		<bndbox>
			<xmin>1359</xmin>
			<ymin>24</ymin>
			<xmax>1547</xmax>
			<ymax>216</ymax>
		</bndbox>
	</object>
	<object>
		<name>Pollos</name>
		<pose>Unspecified</pose>
		<truncated>0</truncated>
		<difficult>0</difficult>
		<bndbox>
			<xmin>870</xmin>
			<ymin>67</ymin>
			<xmax>1108</xmax>
			<ymax>307</ymax>
		</bndbox>
	</object>
	<object>
		<name>Pollos</name>
		<pose>Unspecified</pose>
		<truncated>0</truncated>
		<difficult>0</difficult>
		<bndbox>
			<xmin>1352</xmin>
			<ymin>271</ymin>
			<xmax>1542</xmax>
			<ymax>522</ymax>
		</bndbox>
	</object>
	<object>
		<name>Pollos</name>
		<pose>Unspecified</pose>
		<truncated>0</truncated>
		<difficult>0</difficult>
		<bndbox>
			<xmin>1286</xmin>
			<ymin>449</ymin>
			<xmax>1538</xmax>
			<ymax>721</ymax>
		</bndbox>
	</object>
	<object>
		<name>Pollos</name>
		<pose>Unspecified</pose>
		<truncated>0</truncated>
		<difficult>0</difficult>
		<bndbox>
			<xmin>1139</xmin>
			<ymin>640</ymin>
			<xmax>1436</xmax>
			<ymax>848</ymax>
		</bndbox>
	</object>
	<object>
		<name>Pollos</name>
		<pose>Unspecified</pose>
		<truncated>0</truncated>
		<difficult>0</difficult>
		<bndbox>
			<xmin>1354</xmin>
			<ymin>730</ymin>
			<xmax>1560</xmax>
			<ymax>1002</ymax>
		</bndbox>
	</object>
	<object>
		<name>Pollos</name>
		<pose>Unspecified</pose>
		<truncated>0</truncated>
		<difficult>0</difficult>
		<bndbox>
			<xmin>1074</xmin>
			<ymin>803</ymin>
			<xmax>1386</xmax>
			<ymax>1063</ymax>
		</bndbox>
	</object>
	<object>
		<name>Pollos</name>
		<pose>Unspecified</pose>
		<truncated>0</truncated>
		<difficult>0</difficult>
		<bndbox>
			<xmin>394</xmin>
			<ymin>549</ymin>
			<xmax>653</xmax>
			<ymax>794</ymax>
		</bndbox>
	</object>
	<object>
		<name>Pollos</name>
		<pose>Unspecified</pose>
		<truncated>0</truncated>
		<difficult>0</difficult>
		<bndbox>
			<xmin>268</xmin>
			<ymin>386</ymin>
			<xmax>471</xmax>
			<ymax>558</ymax>
		</bndbox>
	</object>
	<object>
		<name>Pollos</name>
		<pose>Unspecified</pose>
		<truncated>0</truncated>
		<difficult>0</difficult>
		<bndbox>
			<xmin>71</xmin>
			<ymin>581</ymin>
			<xmax>324</xmax>
			<ymax>753</ymax>
		</bndbox>
	</object>
	<object>
		<name>Pollos</name>
		<pose>Unspecified</pose>
		<truncated>0</truncated>
		<difficult>0</difficult>
		<bndbox>
			<xmin>288</xmin>
			<ymin>271</ymin>
			<xmax>517</xmax>
			<ymax>409</ymax>
		</bndbox>
	</object>
	<object>
		<name>Pollos</name>
		<pose>Unspecified</pose>
		<truncated>0</truncated>
		<difficult>0</difficult>
		<bndbox>
			<xmin>254</xmin>
			<ymin>19</ymin>
			<xmax>471</xmax>
			<ymax>205</ymax>
		</bndbox>
	</object>
	<object>
		<name>Pollos</name>
		<pose>Unspecified</pose>
		<truncated>0</truncated>
		<difficult>0</difficult>
		<bndbox>
			<xmin>82</xmin>
			<ymin>51</ymin>
			<xmax>236</xmax>
			<ymax>237</ymax>
		</bndbox>
	</object>
	<object>
		<name>Pollos</name>
		<pose>Unspecified</pose>
		<truncated>0</truncated>
		<difficult>0</difficult>
		<bndbox>
			<xmin>154</xmin>
			<ymin>178</ymin>
			<xmax>372</xmax>
			<ymax>379</ymax>
		</bndbox>
	</object>
	<object>
		<name>Pollos</name>
		<pose>Unspecified</pose>
		<truncated>0</truncated>
		<difficult>0</difficult>
		<bndbox>
			<xmin>19</xmin>
			<ymin>169</ymin>
			<xmax>150</xmax>
			<ymax>391</ymax>
		</bndbox>
	</object>
	<object>
		<name>Pollos</name>
		<pose>Unspecified</pose>
		<truncated>0</truncated>
		<difficult>0</difficult>
		<bndbox>
			<xmin>206</xmin>
			<ymin>0</ymin>
			<xmax>390</xmax>
			<ymax>126</ymax>
		</bndbox>
	</object>
	<object>
		<name>Pollos</name>
		<pose>Unspecified</pose>
		<truncated>0</truncated>
		<difficult>0</difficult>
		<bndbox>
			<xmin>234</xmin>
			<ymin>852</ymin>
			<xmax>465</xmax>
			<ymax>1029</ymax>
		</bndbox>
	</object>
</annotation>